{"type":"FeatureCollection","crs": { "type": "name", "properties": { "name": "urn:ogc:def:crs:ESPG:4326" } },"features":[{"type":"Feature","geometry":{"type":"Point","coordinates":[-73.992276237174266,40.759452594381450]},"properties":{"id":0}},{"type":"Feature","geometry":{"type":"Point","coordinates":[-73.990183342582114,40.761338075271560]},"properties":{"id":"15.421878"}},{"type":"Feature","geometry":{"type":"Point","coordinates":[-73.991140101215279,40.760933963739184]},"properties":{"id":1}},{"type":"Feature","geometry":{"type":"Point","coordinates":[-73.990640604768586,40.760249010328486]},"properties":{"id":2}},{"type":"Feature","geometry":{"type":"Point","coordinates":[-73.990801841111818,40.760055079723948]},"properties":{"id":3}},{"type":"Feature","geometry":{"type":"Point","coordinates":[-73.991637309820902,40.760162505694922]},"properties":{"id":4}},{"type":"Feature","geometry":{"type":"Point","coordinates":[-73.992195067770496,40.759494633045250]},"properties":{"id":5}},{"type":"Feature","geometry":{"type":"Point","coordinates":[-73.990626646198763,40.759971575606500]},"properties":{"id":6}},{"type":"Feature","geometry":{"type":"Point","coordinates":[-73.991444828723402,40.759459503855403]},"properties":{"id":7}},{"type":"Feature","geometry":{"type":"Point","coordinates":[-73.990011143742294,40.760004398042113]},"properties":{"id":8}},{"type":"Feature","geometry":{"type":"Point","coordinates":[-73.990711787651804,40.760005959654855]},"properties":{"id":9}},{"type":"Feature","geometry":{"type":"Point","coordinates":[-73.991037086403097,40.760102209126195]},"properties":{"id":10}},{"type":"Feature","geometry":{"type":"Point","coordinates":[-73.991037086403097,40.760102209126195]},"properties":{"id":11}}]}
