{"type":"FeatureCollection","crs": { "type": "name", "properties": { "name": "urn:ogc:def:crs:ESPG:4326" } },"features":[{"type":"Feature","geometry":{"type":"Point","coordinates":[-73.991248892213306,40.758914956795095]},"properties":{"id":0}},{"type":"Feature","geometry":{"type":"Point","coordinates":[-73.992711385163460,40.761411715734674]},"properties":{"id":"15.421878"}},{"type":"Feature","geometry":{"type":"Point","coordinates":[-73.991721524484461,40.762811853457656]},"properties":{"id":1}},{"type":"Feature","geometry":{"type":"Point","coordinates":[-73.991721524484461,40.762811853457656]},"properties":{"id":2}}]}
