{"type":"FeatureCollection","crs": { "type": "name", "properties": { "name": "urn:ogc:def:crs:ESPG:4326" } },"features":[{"type":"Feature","geometry":{"type":"Point","coordinates":[-73.988813596761418,40.764132643410662]},"properties":{"id":0}},{"type":"Feature","geometry":{"type":"Point","coordinates":[-73.996504016668965,40.758743404115954]},"properties":{"id":"15.421878"}},{"type":"Feature","geometry":{"type":"Point","coordinates":[-73.996140564653729,40.762835564868404]},"properties":{"id":1}},{"type":"Feature","geometry":{"type":"Point","coordinates":[-73.996140564653729,40.762835564868404]},"properties":{"id":2}}]}
