{"type":"FeatureCollection","crs": { "type": "name", "properties": { "name": "urn:ogc:def:crs:ESPG:4326" } },"features":[{"type":"Feature","geometry":{"type":"Point","coordinates":[-73.964441977047528,40.802582207227807]},"properties":{"id":0}},{"type":"Feature","geometry":{"type":"Point","coordinates":[-73.964312284576835,40.802718725618028]},"properties":{"id":"15.421878"}},{"type":"Feature","geometry":{"type":"Point","coordinates":[-73.964312284576835,40.802718725618028]},"properties":{"id":1}}]}
